{
    "id": "huevos-rancheros-ish-bake",
    "link": "https://tasty.co/recipe/huevos-rancheros-ish-bake",
    "name": "Huevos Rancheros-ish Bake Recipe by Tasty",
    "image": "https://img.buzzfeed.com/thumbnailer-prod-us-east-1/c5ae61ebfc8b483d8688e23f45bfa1de/BFV5588_HUEVOSRANCHEROS-ISHBAKE_FBEXPORT1080SQ.jpg",
    "description": "Here's what you need: vegetable oil, corn tortillas, black beans, mexican blend cheese, pico de gallo, egg, red enchilada sauce, fresh cilantro, cotija cheese, cream mexicana",
    "recipeCategory": "Breakfast",
    "recipeCuisine": "Fusion",
    "recipeIngredient": [
        "1 cup Vegetable Oil",
        "5 Corn Tortillas (cut 4 of them in half)",
        "14 oz. can Black Beans",
        "1 cup Mexican Blend Cheese",
        "1 1/2 cup Pico de Gallo",
        "6 Eggs",
        "1/2 cup Red Enchilada Sauce",
        "Cilantro",
        "Cotija Cheese",
        "Cream Mexicana or Sour Cream"
    ],
    "recipeInstructionSteps": [
        "Preheat your oven to 375\u02daF (190\u02daC)",
        "In vegetable oil, lightly fry your corn tortillas. Drain on a paper towel.",
        "In a 9 inch (25cm) cast iron skillet, arrange your lightly fried tortillas so they cover the bottom of the skillet.",
        "Add black beans evenly over tortillas. (Some will fall in-between the tortillas, thats ok!)",
        "Sprinkle Mexican blend cheese over the black beans.",
        "Add pico de gallo on top of the cheese.",
        "Using the back of a large spoon, create 6 wells in the pico de gallo for the eggs to rest in.",
        "Crack one egg into each well (6 wells for 6 eggs).",
        "Pour enchilada sauce over everything!",
        "Bake for 20-25 minutes. Check on it often to make sure your yolks don\u2019t overcook!",
        "Top with your favorite huevos rancheros toppings.",
        "Enjoy!"
    ]
}